catc/__init__.py
catc/__main__.py
catc/cli.py
catc/component.py
catc/concatenator.py
catc/config/__init__.py
catc/config/_model.py
catc/config/_values.py
catc/config/generate.py
catc/config/schema.json
catc/logger/__init__.py
catc/logger/_click_logger.py
catc/logger/_logger.py
catc/logger/_noop_logger.py
catc/utils/__init__.py
catc/utils/mapping/__init__.py
catc/utils/mapping/_subscriptable.py
catc-0.1.1.dist-info/LICENSE
catc-0.1.1.dist-info/METADATA
catc-0.1.1.dist-info/WHEEL
catc-0.1.1.dist-info/entry_points.txt
catc-0.1.1.dist-info/RECORD
